{"name":"Quickhost","tagline":"A localhost configuration file creator","body":"### Welcome to the Quickhosts read me page\r\nQuickhost is a small tool we built for easy setup of apache virtual hosts.\r\n\r\nA note on Apache setup: we assume, and sincerely hope, you've setup Apache with a _sites-available_ folder which contains your *.conf files, and a _sites-enabled_ containing symlinks to those .conf files.\r\n\r\nTo install Quickhost, run the following command:\r\n\r\n`\r\nsudo cd /usr/local/bin && sudo git clone git://github.com/maartenJacobs/quickhost.git quickhost_files && sudo mv quickhost_files/* . && sudo rm -Rf quickhost_files\r\n`\r\n\r\n\r\n### Authors and Contributors\r\nCreated by Maarten Jacobs (@maartenJacobs)","google":"UA-34880992-1","note":"Don't delete this file! It's used internally to help with page regeneration."}